pyquoridor/__init__.py
pyquoridor/board.py
pyquoridor/board_setups.py
pyquoridor/exceptions.py
pyquoridor/main.py
pyquoridor/pawn.py
pyquoridor/square.py
pyquoridor/tests.py
pyquoridor/utils.py
pyquoridor-0.0.4.dist-info/LICENSE
pyquoridor-0.0.4.dist-info/METADATA
pyquoridor-0.0.4.dist-info/WHEEL
pyquoridor-0.0.4.dist-info/top_level.txt
pyquoridor-0.0.4.dist-info/RECORD
