Metadata-Version: 2.2
Name: pyquoridor
Version: 0.0.4
Summary: An easy-to-use, lightweight Python library for Quoridor
Author-email: Ramon Viñas Torné <playquoridor@gmail.com>
Project-URL: Homepage, https://github.com/playquoridor/python-quoridor
Project-URL: Issues, https://github.com/playquoridor/python-quoridor/issues
Classifier: Programming Language :: Python :: 3
Classifier: License :: OSI Approved :: MIT License
Classifier: Operating System :: OS Independent
Requires-Python: >=3.8
License-File: LICENSE
Requires-Dist: numpy
